{
  "updatedAt": "2026-03-20T09:46:39.425Z",
  "updatedAtJST": "2026-03-20T18:46:39.425+09:00",
  "date": "2026-03-20",
  "timeOfDay": "evening",
  "topPhrases": [
    {
      "id": "temp.absolute.cold",
      "topic": "temp",
      "text": "夜は冷えますね",
      "weight": 65
    },
    {
      "id": "temp.delta",
      "topic": "temp",
      "text": "昨日より寒いですね",
      "weight": 50
    },
    {
      "id": "rain.today.probable",
      "topic": "rain",
      "text": "これから雨降るみたいですね",
      "weight": 65
    }
  ],
  "byTopic": {
    "temp": {
      "header": "気温",
      "phrases": [
        {
          "id": "temp.absolute.cold",
          "text": "夜は冷えますね",
          "weight": 65
        },
        {
          "id": "temp.delta",
          "text": "昨日より寒いですね",
          "weight": 50
        }
      ]
    },
    "rain": {
      "header": "雨",
      "phrases": [
        {
          "id": "rain.today.probable",
          "text": "これから雨降るみたいですね",
          "weight": 65
        }
      ]
    },
    "feel": {
      "header": "体感",
      "phrases": [
        {
          "id": "feel.wind.strong",
          "text": "今日は風強かったらしいですね",
          "weight": 58
        }
      ]
    },
    "season": {
      "header": "季節",
      "phrases": [
        {
          "id": "season.feel.winter-like",
          "text": "冬っぽいですね",
          "weight": 60
        },
        {
          "id": "season.transition.seasonal-shift",
          "text": "春の気配がしますね",
          "weight": 58
        }
      ]
    },
    "comparison": {
      "header": "例年比較",
      "phrases": [
        {
          "id": "comparison.normal.colder",
          "text": "この時期にしては寒いですね",
          "weight": 54
        }
      ]
    },
    "fallback": {
      "header": "その他",
      "phrases": []
    }
  },
  "details": {
    "maxTemp": 10.5,
    "minTemp": 5.8,
    "yesterdayDiff": "-6.8",
    "apparentMax": 9.3,
    "apparentMin": 4,
    "apparentDeltaMax": "-1.2",
    "apparentDeltaMin": "-1.8",
    "rain": 0.9,
    "rainProbToday": 78,
    "rainProbTomorrow": 3,
    "windMax": 5.6,
    "gustMax": 20.2,
    "humidity": 79,
    "sunrise": "2026-03-20T05:45",
    "sunset": "2026-03-20T17:52",
    "code": 51
  }
}